{
  "version": "1.3.3",
  "syncMode": "incremental",
  "generatedAt": "2026-01-21T06:37:13.897Z",
  "totalCount": 20,
  "icons": [
    {
      "name": "Icon成员管理",
      "originalName": "成员管理",
      "svgPath": "svg/成员管理.svg",
      "componentPath": "src/icons/Icon成员管理.tsx",
      "size": {
        "width": 120,
        "height": 120
      },
      "uploadedAt": "2026-01-21T06:37:13.897Z"
    },
    {
      "name": "IconBangZhuShuoMing",
      "originalName": "å¸®å©è¯´æ",
      "svgPath": "svg/å¸®å©è¯´æ.svg",
      "componentPath": "src/icons/IconBangZhuShuoMing.tsx",
      "size": {
        "width": 24,
        "height": 24
      }
    },
    {
      "name": "IconBaoGaoZhuShou",
      "originalName": "æ¥åå©æ",
      "svgPath": "svg/æ¥åå©æ.svg",
      "componentPath": "src/icons/IconBaoGaoZhuShou.tsx",
      "size": {
        "width": 120,
        "height": 120
      }
    },
    {
      "name": "IconChengYuanGuanLi",
      "originalName": "æåç®¡ç",
      "svgPath": "svg/æåç®¡ç.svg",
      "componentPath": "src/icons/IconChengYuanGuanLi.tsx",
      "size": {
        "width": 120,
        "height": 120
      }
    },
    {
      "name": "IconFangDa",
      "originalName": "æ¾å¤§",
      "svgPath": "svg/æ¾å¤§.svg",
      "componentPath": "src/icons/IconFangDa.tsx",
      "size": {
        "width": 24,
        "height": 24
      }
    },
    {
      "name": "IconFrame",
      "originalName": "Frame",
      "svgPath": "svg/Frame.svg",
      "componentPath": "src/icons/IconFrame.tsx",
      "size": {
        "width": 24,
        "height": 24
      }
    },
    {
      "name": "IconQiYeBan",
      "originalName": "ä¼ä¸ç",
      "svgPath": "svg/ä¼ä¸ç.svg",
      "componentPath": "src/icons/IconQiYeBan.tsx",
      "size": {
        "width": 120,
        "height": 120
      }
    },
    {
      "name": "IconSouSuoZhuShou",
      "originalName": "æç´¢å©æ",
      "svgPath": "svg/æç´¢å©æ.svg",
      "componentPath": "src/icons/IconSouSuoZhuShou.tsx",
      "size": {
        "width": 120,
        "height": 119
      }
    },
    {
      "name": "IconSuoXiao",
      "originalName": "ç¼©å°",
      "svgPath": "svg/ç¼©å°.svg",
      "componentPath": "src/icons/IconSuoXiao.tsx",
      "size": {
        "width": 24,
        "height": 24
      }
    },
    {
      "name": "IconWangYeXiaZai",
      "originalName": "ç½é¡µä¸è½½",
      "svgPath": "svg/ç½é¡µä¸è½½.svg",
      "componentPath": "src/icons/IconWangYeXiaZai.tsx",
      "size": {
        "width": 24,
        "height": 24
      }
    },
    {
      "name": "IconWenDaZhuShou",
      "originalName": "é®ç­å©æ",
      "svgPath": "svg/é®ç­å©æ.svg",
      "componentPath": "src/icons/IconWenDaZhuShou.tsx",
      "size": {
        "width": 120,
        "height": 120
      }
    },
    {
      "name": "IconXiaoXi",
      "originalName": "æ¶æ¯",
      "svgPath": "svg/æ¶æ¯.svg",
      "componentPath": "src/icons/IconXiaoXi.tsx",
      "size": {
        "width": 24,
        "height": 24
      }
    },
    {
      "name": "IconXiaZaiZhuShou",
      "originalName": "ä¸è½½å©æ",
      "svgPath": "svg/ä¸è½½å©æ.svg",
      "componentPath": "src/icons/IconXiaZaiZhuShou.tsx",
      "size": {
        "width": 120,
        "height": 120
      }
    },
    {
      "name": "IconXinXiGuanLi",
      "originalName": "ä¿¡æ¯ç®¡ç",
      "svgPath": "svg/ä¿¡æ¯ç®¡ç.svg",
      "componentPath": "src/icons/IconXinXiGuanLi.tsx",
      "size": {
        "width": 120,
        "height": 120
      }
    },
    {
      "name": "IconXinZeng",
      "originalName": "æ°å¢",
      "svgPath": "svg/æ°å¢.svg",
      "componentPath": "src/icons/IconXinZeng.tsx",
      "size": {
        "width": 24,
        "height": 24
      }
    },
    {
      "name": "IconXiTongPeiZhi",
      "originalName": "ç³»ç»éç½®",
      "svgPath": "svg/ç³»ç»éç½®.svg",
      "componentPath": "src/icons/IconXiTongPeiZhi.tsx",
      "size": {
        "width": 120,
        "height": 120
      }
    },
    {
      "name": "IconYanZhengMa",
      "originalName": "éªè¯ç ",
      "svgPath": "svg/éªè¯ç .svg",
      "componentPath": "src/icons/IconYanZhengMa.tsx",
      "size": {
        "width": 24,
        "height": 24
      }
    },
    {
      "name": "IconYunYingGuanLi",
      "originalName": "è¿è¥ç®¡ç",
      "svgPath": "svg/è¿è¥ç®¡ç.svg",
      "componentPath": "src/icons/IconYunYingGuanLi.tsx",
      "size": {
        "width": 120,
        "height": 120
      }
    },
    {
      "name": "IconZhanKai",
      "originalName": "å±å¼",
      "svgPath": "svg/å±å¼.svg",
      "componentPath": "src/icons/IconZhanKai.tsx",
      "size": {
        "width": 24,
        "height": 24
      }
    },
    {
      "name": "IconZhengQue",
      "originalName": "æ­£ç¡®",
      "svgPath": "svg/æ­£ç¡®.svg",
      "componentPath": "src/icons/IconZhengQue.tsx",
      "size": {
        "width": 24,
        "height": 24
      }
    }
  ]
}